{"name":"SICP-solutions","note":"Don't delete this file! It's used internally to help with page regeneration.","google":"","tagline":"Solutions of SICP's exercises","body":"### Welcome to My SICP-solutions.\r\nI want to record my solutions of SICP's exercises and I use the GitHub Pages to create this beautiful page for all of my projects. \r\n\r\nNow, I am working in the exercise of chapter1 of this book. \r\n\r\n```\r\n$ git clone git@github.com:HengfengLi/SICP-Solutions.git\r\n```\r\n\r\n\r\n\r\n### Authors and Contributors\r\nIn 2012, Hengfeng Li (@HengfengLi)\r\n\r\n### Support or Contact\r\nHaving trouble with SICP-solutions? Contact hengfeng12345@gmail.com and I’ll help you sort it out."}